pylon_client/__init__.py
pylon_client/_internal/__init__.py
pylon_client/_internal/config.py
pylon_client/_internal/docker_manager.py
pylon_client/_internal/asynchronous/__init__.py
pylon_client/_internal/asynchronous/api.py
pylon_client/_internal/asynchronous/client.py
pylon_client/_internal/asynchronous/communicators.py
pylon_client/_internal/asynchronous/config.py
pylon_client/_internal/pylon_commons/__init__.py
pylon_client/_internal/pylon_commons/apiver.py
pylon_client/_internal/pylon_commons/bodies.py
pylon_client/_internal/pylon_commons/constants.py
pylon_client/_internal/pylon_commons/currency.py
pylon_client/_internal/pylon_commons/endpoints.py
pylon_client/_internal/pylon_commons/exceptions.py
pylon_client/_internal/pylon_commons/models.py
pylon_client/_internal/pylon_commons/requests.py
pylon_client/_internal/pylon_commons/responses.py
pylon_client/_internal/pylon_commons/settings.py
pylon_client/_internal/pylon_commons/types.py
pylon_client/_internal/sync/__init__.py
pylon_client/_internal/sync/api.py
pylon_client/_internal/sync/client.py
pylon_client/_internal/sync/communicators.py
pylon_client/_internal/sync/config.py
pylon_client/v1/__init__.py
bittensor_pylon_client-1.5.0.dist-info/METADATA
bittensor_pylon_client-1.5.0.dist-info/WHEEL
bittensor_pylon_client-1.5.0.dist-info/RECORD
