Metadata-Version: 2.4
Name: bittensor-pylon-client
Version: 1.5.0
Summary: Bittensor Pylon client library
Project-URL: homepage, https://github.com/backend-developers-ltd/bittensor-pylon
Project-URL: repository, https://github.com/backend-developers-ltd/bittensor-pylon
Author-email: Reef Technologies <opensource@reef.pl>
Requires-Python: >=3.11
Requires-Dist: apscheduler
Requires-Dist: docker
Requires-Dist: httpx
Requires-Dist: pydantic-settings>=2.0
Requires-Dist: pydantic>=2.0
Requires-Dist: tenacity
Provides-Extra: dev
Requires-Dist: polyfactory>=2.22.2; extra == 'dev'
Requires-Dist: pyright; extra == 'dev'
Requires-Dist: pytest; extra == 'dev'
Requires-Dist: pytest-asyncio>=1.0.0; extra == 'dev'
Requires-Dist: respx>=0.22.0; extra == 'dev'
Requires-Dist: ruff; extra == 'dev'
